teaspoon/__init__.py
teaspoon/DAF/data_assimilation.py
teaspoon/DAF/forecasting.py
teaspoon/ML/Base.py
teaspoon/ML/PD_Classification.py
teaspoon/ML/__init__.py
teaspoon/ML/feature_functions.py
teaspoon/ML/load_datasets.py
teaspoon/ML/datasets/__init__.py
teaspoon/ML/datasets/mnist.pickle
teaspoon/ML/datasets/mpeg7.pickle
teaspoon/ML/datasets/shrec14.pickle
teaspoon/MakeData/PointCloud.py
teaspoon/MakeData/__init__.py
teaspoon/MakeData/DynSysLib/DynSysLib.py
teaspoon/MakeData/DynSysLib/UserGuide.py
teaspoon/MakeData/DynSysLib/__init__.py
teaspoon/MakeData/DynSysLib/autonomous_dissipative_flows.py
teaspoon/MakeData/DynSysLib/conservative_flows.py
teaspoon/MakeData/DynSysLib/delayed_flows.py
teaspoon/MakeData/DynSysLib/driven_dissipative_flows.py
teaspoon/MakeData/DynSysLib/maps.py
teaspoon/MakeData/DynSysLib/medical_data.py
teaspoon/MakeData/DynSysLib/noise_models.py
teaspoon/MakeData/DynSysLib/periodic_functions.py
teaspoon/MakeData/DynSysLib/Data/__init__.py
teaspoon/MakeData/DynSysLib/Data/EEG/S056.txt
teaspoon/MakeData/DynSysLib/Data/EEG/Z093.txt
teaspoon/MakeData/DynSysLib/Data/EEG/__init__.py
teaspoon/SP/StochasticP.py
teaspoon/SP/__init__.py
teaspoon/SP/adaptivePart.py
teaspoon/SP/network.py
teaspoon/SP/network_tools.py
teaspoon/SP/parameter_path_opt.py
teaspoon/SP/texture_analysis.py
teaspoon/SP/tsa_tools.py
teaspoon/SP/information/__init__.py
teaspoon/SP/information/entropy.py
teaspoon/TDA/Distance.py
teaspoon/TDA/Draw.py
teaspoon/TDA/Magnitude.py
teaspoon/TDA/PHN.py
teaspoon/TDA/Persistence.py
teaspoon/TDA/SLSP.py
teaspoon/TDA/SLSP_tools.py
teaspoon/TDA/__init__.py
teaspoon/TDA/fast_zigzag.py
teaspoon/parameter_selection/FNN_n.py
teaspoon/parameter_selection/MI_delay.py
teaspoon/parameter_selection/MsPE.py
teaspoon/parameter_selection/PAMI_delay.py
teaspoon/parameter_selection/__init__.py
teaspoon/parameter_selection/autocorrelation.py
teaspoon/parameter_selection/delay_LMS.py
teaspoon-1.5.28.dist-info/licenses/LICENSE.txt
teaspoon-1.5.28.dist-info/METADATA
teaspoon-1.5.28.dist-info/WHEEL
teaspoon-1.5.28.dist-info/dependency_links.txt
teaspoon-1.5.28.dist-info/top_level.txt
teaspoon-1.5.28.dist-info/RECORD
