Metadata-Version: 2.4
Name: teaspoon
Version: 1.5.28
Summary: A Topological Signal Processing Package
Author-email: Elizabeth Munch <muncheli@msu.edu>, Firas Khasawneh <khasawn3@msu.edu>
Project-URL: repository, https://github.com/TeaspoonTDA/teaspoon
Project-URL: homepage, https://github.com/TeaspoonTDA/teaspoon
Project-URL: documentation, https://teaspoontda.github.io/teaspoon/
Classifier: Programming Language :: Python :: 3
Classifier: Operating System :: OS Independent
Requires-Python: >=3.9
License-File: LICENSE.txt
Requires-Dist: cycler>=0.11.0
Requires-Dist: fonttools>=4.34.4
Requires-Dist: joblib>=1.2.0
Requires-Dist: kiwisolver>=1.4.4
Requires-Dist: matplotlib>=3.5.2
Requires-Dist: networkx>=3.1
Requires-Dist: numpy>=1.23.1
Requires-Dist: packaging>=23.1
Requires-Dist: Pillow>=9.3.0
Requires-Dist: POT>=0.8.2
Requires-Dist: pyentrp>=0.7.1
Requires-Dist: pyparsing<3.1,>=2.3.1
Requires-Dist: python-dateutil>=2.8.2
Requires-Dist: scikit-learn>=1.1.1
Requires-Dist: scipy>=1.8.1
Requires-Dist: six>=1.16.0
Requires-Dist: threadpoolctl>=3.1.0
Requires-Dist: ripser>=0.6.4
Requires-Dist: sympy>=1.11.1
Requires-Dist: sortedcontainers>=2.4.0
Requires-Dist: persim
Requires-Dist: pandas>=1.4.1
Requires-Dist: gudhi
Requires-Dist: numba
Requires-Dist: importlib_resources
Requires-Dist: pooch
Requires-Dist: ddeint
Provides-Extra: full
Requires-Dist: teaspoon[full]; extra == "full"
Requires-Dist: tensorflow; extra == "full"
Requires-Dist: eagerpy; extra == "full"
Requires-Dist: torchdiffeq; extra == "full"
Requires-Dist: torch; extra == "full"
Dynamic: license-file
